audio_reads/__init__.py
audio_reads/__main__.py
audio_reads/article.py
audio_reads/chunks.py
audio_reads/cli.py
audio_reads/common.py
audio_reads/elevenlabs.py
audio_reads/filename.py
audio_reads/openai.py
audio_reads-0.1.21.dist-info/LICENSE.md
audio_reads-0.1.21.dist-info/METADATA
audio_reads-0.1.21.dist-info/WHEEL
audio_reads-0.1.21.dist-info/entry_points.txt
audio_reads-0.1.21.dist-info/top_level.txt
audio_reads-0.1.21.dist-info/RECORD
