Metadata-Version: 2.1
Name: audio-reads
Version: 0.1.21
Summary: CLI tool for converting articles to podcasts
Author: Ivan Kovnatsky
License: MIT
Project-URL: Homepage, https://github.com/ivankovnatsky/audio-reads
Project-URL: Changelog, https://github.com/ivankovnatsky/audio-reads/releases
Project-URL: Issues, https://github.com/ivankovnatsky/audio-reads/issues
Project-URL: CI, https://github.com/ivankovnatsky/audio-reads/actions
Classifier: License :: OSI Approved :: MIT License
Requires-Python: >=3.8
License-File: LICENSE.md
Requires-Dist: beautifulsoup4
Requires-Dist: click
Requires-Dist: elevenlabs
Requires-Dist: lxml[html_clean]
Requires-Dist: openai >=1.0
Requires-Dist: playwright
Requires-Dist: pydub
Requires-Dist: readability-lxml
Requires-Dist: requests
Requires-Dist: simpleaudio ; sys_platform == "darwin"
Provides-Extra: test
Requires-Dist: pytest ; extra == 'test'
Requires-Dist: cogapp ; extra == 'test'
